pykanto/__init__.py
pykanto/dataset.py
pykanto/parameters.py
pykanto/plot.py
pykanto/app/__init__.py
pykanto/app/data.py
pykanto/app/main.py
pykanto/app/theme.yaml
pykanto/app/static/lasso.png
pykanto/app/static/pykanto-logo.svg
pykanto/app/templates/index.html
pykanto/app/templates/styles.css
pykanto/data/raw/AM/20210502_040000.WAV
pykanto/data/raw/AM/20210502_040000.xml
pykanto/data/raw/BENGALESE_FINCH/bird_3/348.wav
pykanto/data/raw/BENGALESE_FINCH/bird_3/348.xml
pykanto/data/raw/BENGALESE_FINCH/bird_3/363.wav
pykanto/data/raw/BENGALESE_FINCH/bird_3/363.xml
pykanto/data/raw/STORM-PETREL/XC46092.wav
pykanto/data/raw/STORM-PETREL/XC46092.xml
pykanto/data/raw/STORM-PETREL/XC663885.wav
pykanto/data/raw/STORM-PETREL/XC663885.xml
pykanto/data/segmented/great_tit/JSON/2021-B32-0415_05-11.JSON
pykanto/data/segmented/great_tit/JSON/2021-B32-0415_05-15.JSON
pykanto/data/segmented/great_tit/JSON/2021-B32-0415_05-21.JSON
pykanto/data/segmented/great_tit/JSON/2021-B32-0415_05-23.JSON
pykanto/data/segmented/great_tit/JSON/2021-B32-0415_05-3.JSON
pykanto/data/segmented/great_tit/JSON/2021-B32-0415_05-6.JSON
pykanto/data/segmented/great_tit/JSON/2021-B32-0415_05-9.JSON
pykanto/data/segmented/great_tit/JSON/2021-B32-0416_04-21.JSON
pykanto/data/segmented/great_tit/JSON/2021-B32-0416_04-23.JSON
pykanto/data/segmented/great_tit/JSON/2021-B32-0416_04-24.JSON
pykanto/data/segmented/great_tit/JSON/2021-B32-0416_05-20.JSON
pykanto/data/segmented/great_tit/JSON/2021-SW83-0418_04-77.JSON
pykanto/data/segmented/great_tit/JSON/2021-SW83-0418_04-78.JSON
pykanto/data/segmented/great_tit/JSON/2021-SW83-0418_04-79.JSON
pykanto/data/segmented/great_tit/JSON/2021-SW83-0418_04-80.JSON
pykanto/data/segmented/great_tit/JSON/2021-SW83-0418_04-81.JSON
pykanto/data/segmented/great_tit/JSON/2021-SW83-0418_04-86.JSON
pykanto/data/segmented/great_tit/JSON/2021-SW83-0418_04-88.JSON
pykanto/data/segmented/great_tit/JSON/2021-SW83-0418_04-91.JSON
pykanto-0.1.8.dist-info/entry_points.txt
pykanto-0.1.8.dist-info/LICENSE
pykanto-0.1.8.dist-info/WHEEL
pykanto-0.1.8.dist-info/METADATA
pykanto-0.1.8.dist-info/RECORD
