Metadata-Version: 2.3
Name: pykanto
Version: 0.1.8
Summary: A library for managing and analysing animal vocalisation data.
Author-email: "Nilo M. Recalde" <nilomerinorecalde@gmail.com>
Requires-Python: >=3.8
Classifier: License :: OSI Approved :: MIT License
Classifier: Development Status :: 4 - Beta
Classifier: Programming Language :: Python :: 3.8
Classifier: Programming Language :: Python :: 3.9
Classifier: Programming Language :: Python :: 3.10
Requires-Dist: pandas >= 1
Requires-Dist: numpy >= 1.17, <1.23.1
Requires-Dist: scipy >= 1.5
Requires-Dist: numba >= 0.49
Requires-Dist: tqdm
Requires-Dist: audio-metadata >= 0.11.1
Requires-Dist: pydantic < 2
Requires-Dist: ray[default]
Requires-Dist: pysoundfile >= 0.9
Requires-Dist: umap-learn >= 0.5
Requires-Dist: joblib >= 1.2.0
Requires-Dist: hdbscan >= 0.8.29
Requires-Dist: seaborn >= 0.11
Requires-Dist: scikit-image >= 0.18
Requires-Dist: librosa >= 0.8, <0.10.0
Requires-Dist: bokeh >=2.3.3, <3.0.0
Requires-Dist: ujson
Requires-Dist: psutil
Requires-Dist: attrs<19.4
Requires-Dist: gitpython
Requires-Dist: typer == 0.6
Requires-Dist: ipywidgets <= 8.0.3 ; extra == "dev"
Requires-Dist: ipykernel < 6.20 ; extra == "dev"
Requires-Dist: pytest >= 7 ; extra == "dev"
Requires-Dist: nox ; extra == "dev"
Requires-Dist: black ; extra == "dev"
Requires-Dist: sphinx <5, >= 3.5.4 ; extra == "doc"
Requires-Dist: sphinx-copybutton ; extra == "doc"
Requires-Dist: sphinx_book_theme == 0.3.3 ; extra == "doc"
Requires-Dist: myst-nb ==  0.17 ; extra == "doc"
Requires-Dist: myst-parser == 0.18 ; extra == "doc"
Requires-Dist: jsonschema == 4.17.3 ; extra == "jupyter"
Requires-Dist: jupyter == 1.0.0 ; extra == "jupyter"
Requires-Dist: jupyter-cache == 0.5.0 ; extra == "jupyter"
Requires-Dist: jupyter-client == 7.4.8 ; extra == "jupyter"
Requires-Dist: jupyter-console == 6.4.4 ; extra == "jupyter"
Requires-Dist: jupyter-core == 5.1.0 ; extra == "jupyter"
Requires-Dist: jupyter-events == 0.5.0 ; extra == "jupyter"
Requires-Dist: jupyter-server == 2.0.1 ; extra == "jupyter"
Requires-Dist: jupyter-server-terminals == 0.4.2 ; extra == "jupyter"
Requires-Dist: jupyterlab-pygments == 0.2.2 ; extra == "jupyter"
Requires-Dist: jupyterlab-widgets == 3.0.4 ; extra == "jupyter"
Requires-Dist: pytest >=7 ; extra == "test"
Project-URL: Documentation, https://nilomr.github.io/pykanto
Project-URL: Source, https://github.com/nilomr/pykanto
Provides-Extra: dev
Provides-Extra: doc
Provides-Extra: jupyter
Provides-Extra: test
